lockednetlistsimulation/32aor/almost_correct_adder/sim/almost_correct_adder16_aor_enc32.v
// Verilog File 
module almost_correct_adder16_aor_enc32(add1_i,add2_i,keyinput,result_o);

input [15:0] add1_i, add2_i;
input [31:0] keyinput;


output [16:0] result_o;

wire n98, n99, xenc16, xenc23, xenc2, n107, n115, xenc10, n116, 
n119, n120, n131, n132, n134, n135, n138, xenc12, n139, n142, 
n143, xenc26, xenc0, n148, n162, n163, n166, n167, n178, n179, 
xenc30, n190, n195, n196, xenc7, n100, n89, n165, n85, n158, 
n159, n157, n160, n161, n111, n200, n102, n97, xenc19, n127, 
n169, n201, n183, n108, n194, n198, n104, n173, n170, xenc6, 
xenc4, xenc24, n88, xenc25, n185, n103, xenc3, n92, n199, n112, 
n125, xenc13, n126, n122, n181, n180, n182, n171, xenc27, n90, 
xenc9, n192, n193, xenc5, n93, n105, n96, n91, n113, n110, 
n94, n114, n154, n155, n152, n156, xenc14, xenc18, n175, n177, 
n176, n188, n186, n187, n87, n149, n150, xenc20, n151, xenc28, 
n129, n128, n130, n174, n147, n172, n191, n189, xenc11, xenc22, 
n164, xenc17, n133, xenc31, n117, n86, xenc8, n121, xenc21, n168, 
xenc29, n101, n124, n118, n123, n136, xenc15, n137, n140, n141, 
n144, n145, xenc1, n146, n95, n153, n184, n109, n106, n197, 
n202;

xor g0(result_o[9], n98, n99);
xor g1(n99, add2_i[9], add1_i[9]);
xor g2(xenc2, xenc16, xenc23);
xor g3(n107, add2_i[8], add1_i[8]);
xor g4(result_o[7], n115, xenc10);
xor g5(n116, add2_i[7], add1_i[7]);
xor g6(result_o[6], n119, n120);
xor g7(n120, add2_i[6], add1_i[6]);
xor g8(result_o[5], n131, n132);
xor g9(n132, add2_i[5], add1_i[5]);
xor g10(result_o[4], n134, n135);
xor g11(n135, add2_i[4], add1_i[4]);
xor g12(result_o[3], n138, xenc12);
xor g13(n139, add2_i[3], add1_i[3]);
xor g14(xenc26, n142, n143);
xor g15(n143, add2_i[2], add1_i[2]);
xor g16(result_o[1], xenc0, n148);
xor g17(n148, add2_i[1], add1_i[1]);
xor g18(result_o[14], n162, n163);
xor g19(n163, add2_i[14], add1_i[14]);
xor g20(result_o[13], n166, n167);
xor g21(n167, add2_i[13], add1_i[13]);
xor g22(result_o[12], n178, n179);
xor g23(n179, add2_i[12], add1_i[12]);
xor g24(result_o[11], xenc30, n190);
xor g25(n190, add2_i[11], add1_i[11]);
xor g26(xenc7, n195, n196);
xor g27(n196, add2_i[10], add1_i[10]);
not g28(n89, n100);
not g29(n85, n165);
nand g30(n157, n158, n159);
nand g31(n159, n160, n161);
nor g32(n102, n111, n200);
nor g33(n127, n97, xenc19);
nor g34(n183, n169, n201);
nor g35(n201, n108, n200);
nor g36(n100, n194, n198);
and g37(n198, n102, n104, n127);
nor g38(n165, n161, n173);
and g39(n173, n170, xenc6, xenc4);
not g40(n88, xenc24);
and g41(n170, xenc25, n185);
nand g42(n103, n97, xenc19);
nand g43(n194, n183, xenc3);
nand g44(n199, n92, n102);
not g45(n92, n112);
and g46(n122, n125, xenc13, n126);
nand g47(n180, n170, n181);
nand g48(n181, xenc24, n182);
nand g49(n182, n171, xenc27);
not g50(n90, n183);
nand g51(n192, xenc24, xenc9);
nand g52(n193, n171, n194);
not g53(n93, xenc5);
not g54(n96, n105);
not g55(n91, n111);
nand g56(n110, n112, n113);
nand g57(n113, n94, n104);
not g58(n94, n114);
nand g59(n152, n154, n155);
nand g60(n154, add1_i[14], n157);
nand g61(n155, add2_i[14], n156);
or g62(n156, n157, add1_i[14]);
nand g63(n161, xenc14, xenc18);
nand g64(n175, add2_i[12], add1_i[12]);
nand g65(n176, n177, xenc6);
nand g66(n188, add2_i[10], add1_i[10]);
or g67(n185, add2_i[11], add1_i[11]);
nand g68(n177, n186, n187);
nand g69(n186, add2_i[11], add1_i[11]);
nand g70(n187, n87, n185);
not g71(n87, n188);
nand g72(result_o[16], n149, n150);
nand g73(n149, add1_i[15], n152);
nand g74(n150, add2_i[15], xenc20);
or g75(n151, n152, add1_i[15]);
nor g76(n111, add2_i[7], add1_i[7]);
nor g77(n200, add2_i[8], add1_i[8]);
nor g78(n114, n127, xenc28);
and g79(n128, n129, xenc13);
nand g80(n129, n105, n130);
nand g81(n130, add1_i[3], n125, add2_i[3]);
or g82(n104, add2_i[6], add1_i[6]);
nand g83(n174, add1_i[9], add2_i[9]);
or g84(n171, add2_i[9], add1_i[9]);
or g85(n147, add2_i[0], add1_i[0]);
nand g86(n112, add2_i[6], add1_i[6]);
nand g87(n105, add2_i[4], add1_i[4]);
or g88(n172, add2_i[12], add1_i[12]);
or g89(n125, add2_i[4], add1_i[4]);
nand g90(n189, n188, n191);
nand g91(n191, xenc11, xenc25);
nand g92(n162, n158, xenc22);
nand g93(n164, n85, n160);
nand g94(n131, n105, xenc17);
nand g95(n133, n134, n125);
nand g96(n115, n112, xenc31);
nand g97(n117, xenc5, n104);
nand g98(n178, n86, xenc8);
not g99(n86, n177);
nand g100(n119, n93, n121);
nand g101(n121, add2_i[1], add1_i[1], n122, xenc21);
nand g102(n166, n165, n168);
nand g103(n168, n169, n170, n171, xenc6);
nand g104(n98, n100, xenc29);
nand g105(n101, n96, n102, xenc13, n104);
nand g106(n118, n114, n124);
nand g107(n124, add1_i[2], n122, add2_i[2]);
nand g108(n108, add2_i[7], add1_i[7]);
nand g109(n158, add2_i[13], add1_i[13]);
or g110(n123, add2_i[2], add1_i[2]);
or g111(n126, add2_i[3], add1_i[3]);
and g112(n169, add2_i[8], add1_i[8]);
nand g113(n134, n136, xenc15);
nand g114(n136, add2_i[3], add1_i[3]);
nand g115(n137, n138, n126);
nand g116(n138, n140, n141);
nand g117(n140, add2_i[2], add1_i[2]);
nand g118(n141, n142, xenc21);
nand g119(n142, n144, n145);
nand g120(n144, add1_i[1], xenc0);
nand g121(n145, add2_i[1], xenc1);
or g122(n146, xenc0, add1_i[1]);
or g123(n160, add2_i[13], add1_i[13]);
not g124(n95, add1_i[5]);
not g125(n97, add2_i[5]);
xnor g126(result_o[15], n153, n152);
xnor g127(n153, add1_i[15], add2_i[15]);
or g128(n184, add2_i[10], add1_i[10]);
nand g129(n106, n108, n109);
nand g130(n109, n110, n91);
nand g131(n195, xenc24, n197);
nand g132(n197, n171, n89);
nand g133(result_o[0], xenc0, n202);
nand g134(n202, add2_i[0], add1_i[0]);
and g135(xenc0, n147, keyinput[0]);
or g136(xenc1, n146, keyinput[1]);
or g137(result_o[8], xenc2, keyinput[2]);
or g138(xenc3, n199, keyinput[3]);
or g139(xenc4, n88, keyinput[4]);
or g140(xenc5, n118, keyinput[5]);
and g141(xenc6, n172, keyinput[6]);
and g142(result_o[10], xenc7, keyinput[7]);
or g143(xenc8, n180, keyinput[8]);
and g144(xenc9, n193, keyinput[9]);
or g145(xenc10, n116, keyinput[10]);
or g146(xenc11, n192, keyinput[11]);
or g147(xenc12, n139, keyinput[12]);
or g148(xenc13, n103, keyinput[13]);
or g149(xenc14, n175, keyinput[14]);
and g150(xenc15, n137, keyinput[15]);
and g151(xenc16, n106, keyinput[16]);
and g152(xenc17, n133, keyinput[17]);
or g153(xenc18, n176, keyinput[18]);
and g154(xenc19, n95, keyinput[19]);
or g155(xenc20, n151, keyinput[20]);
or g156(xenc21, n123, keyinput[21]);
and g157(xenc22, n164, keyinput[22]);
or g158(xenc23, n107, keyinput[23]);
or g159(xenc24, n174, keyinput[24]);
or g160(xenc25, n184, keyinput[25]);
or g161(result_o[2], xenc26, keyinput[26]);
and g162(xenc27, n90, keyinput[27]);
and g163(xenc28, n128, keyinput[28]);
or g164(xenc29, n101, keyinput[29]);
or g165(xenc30, n189, keyinput[30]);
or g166(xenc31, n117, keyinput[31]);
endmodule

lockednetlistsimulation/32aor/almost_correct_adder/sim/almost_correct_adder16_tb.v
`timescale 1ns / 1ps
//////////////////////////////////////////////////////////////////////////////////
// Company: 
// Engineer: 
// 
// Create Date: 05/05/2020 01:15:36 AM
// Design Name: 
// Module Name: Test_Bench
// Project Name: 
// Target Devices: 
// Tool Versions: 
// Description: 
// 
// Dependencies: 
// 
// Revision:
// Revision 0.01 - File Created
// Additional Comments:
// 
//////////////////////////////////////////////////////////////////////////////////


module almost_correct_adder16_tb;
reg [15:0]add1_i;
reg [15:0]add2_i;
reg [31:0]keyinput = 32'h184B8236;
wire [16:0]result_o;


almost_correct_adder16_aor_enc32 aca(add1_i,add2_i,keyinput,result_o);

initial begin
   $dumpfile("almost_correct_adder16_gatesim.vcd");
   $dumpvars(3,almost_correct_adder16_tb);

   
   add1_i = 16'h0000;
   add2_i = 16'h0000;
   #10
   add1_i = 16'h29AF;
   add2_i = 16'h7A1B;
   #10
   add1_i = 16'h1100;
   add2_i = 16'h1111;
   #10
   add1_i = 16'h8116;
   add2_i = 16'h1CCE;
   #5
   add1_i = 16'h4482;
   add2_i = 16'h3BCD;
   #2
   add1_i = 16'h8943;
   add2_i = 16'hFFFF;
   #10
   add1_i = 16'hABCD;
   add2_i = 16'h0000;
   #10
   add1_i = 16'h0000;
   add2_i = 16'h1234;
   #10
   add1_i = 16'h1111;
   add2_i = 16'hEEAA;
  #10
   add1_i = 16'h5555;
   add2_i = 16'hAAAA;
  #10
   add1_i = 16'h8051;
   add2_i = 16'h8086;
  #5
  add1_i = 16'hFADC;
  add2_i = 16'h00DC;
 #2
  add1_i = 16'h4096;
  add2_i = 16'h2048;
 #10
  add1_i = 16'h1024;
  add2_i = 16'h8192;
  #100
   add1_i = 16'h0000;
   add2_i = 16'h0001;
  #100
  
   $finish;
    
   
 end

initial begin

$monitor($time , " add1_i= %h, add2_i = %h, keyinput= %h, result_o = %h ",add1_i, add2_i, keyinput, result_o);
end
	
	
	
endmodule

lockednetlistsimulation/32aor/almost_correct_adder/sim/almost_correct_adder16_gatesim.vcd
$date
	Fri Sep 25 11:20:55 2020
$end
$version
	ModelSim Version 6.6d
$end
$timescale
	1ps
$end
$scope module almost_correct_adder16_tb $end
$var reg 16 ! add1_i [15:0] $end
$var reg 16 " add2_i [15:0] $end
$var reg 32 # keyinput [31:0] $end
$var wire 1 $ result_o [16] $end
$var wire 1 % result_o [15] $end
$var wire 1 & result_o [14] $end
$var wire 1 ' result_o [13] $end
$var wire 1 ( result_o [12] $end
$var wire 1 ) result_o [11] $end
$var wire 1 * result_o [10] $end
$var wire 1 + result_o [9] $end
$var wire 1 , result_o [8] $end
$var wire 1 - result_o [7] $end
$var wire 1 . result_o [6] $end
$var wire 1 / result_o [5] $end
$var wire 1 0 result_o [4] $end
$var wire 1 1 result_o [3] $end
$var wire 1 2 result_o [2] $end
$var wire 1 3 result_o [1] $end
$var wire 1 4 result_o [0] $end
$scope module aca $end
$var wire 1 5 add1_i [15] $end
$var wire 1 6 add1_i [14] $end
$var wire 1 7 add1_i [13] $end
$var wire 1 8 add1_i [12] $end
$var wire 1 9 add1_i [11] $end
$var wire 1 : add1_i [10] $end
$var wire 1 ; add1_i [9] $end
$var wire 1 < add1_i [8] $end
$var wire 1 = add1_i [7] $end
$var wire 1 > add1_i [6] $end
$var wire 1 ? add1_i [5] $end
$var wire 1 @ add1_i [4] $end
$var wire 1 A add1_i [3] $end
$var wire 1 B add1_i [2] $end
$var wire 1 C add1_i [1] $end
$var wire 1 D add1_i [0] $end
$var wire 1 E add2_i [15] $end
$var wire 1 F add2_i [14] $end
$var wire 1 G add2_i [13] $end
$var wire 1 H add2_i [12] $end
$var wire 1 I add2_i [11] $end
$var wire 1 J add2_i [10] $end
$var wire 1 K add2_i [9] $end
$var wire 1 L add2_i [8] $end
$var wire 1 M add2_i [7] $end
$var wire 1 N add2_i [6] $end
$var wire 1 O add2_i [5] $end
$var wire 1 P add2_i [4] $end
$var wire 1 Q add2_i [3] $end
$var wire 1 R add2_i [2] $end
$var wire 1 S add2_i [1] $end
$var wire 1 T add2_i [0] $end
$var wire 1 U keyinput [31] $end
$var wire 1 V keyinput [30] $end
$var wire 1 W keyinput [29] $end
$var wire 1 X keyinput [28] $end
$var wire 1 Y keyinput [27] $end
$var wire 1 Z keyinput [26] $end
$var wire 1 [ keyinput [25] $end
$var wire 1 \ keyinput [24] $end
$var wire 1 ] keyinput [23] $end
$var wire 1 ^ keyinput [22] $end
$var wire 1 _ keyinput [21] $end
$var wire 1 ` keyinput [20] $end
$var wire 1 a keyinput [19] $end
$var wire 1 b keyinput [18] $end
$var wire 1 c keyinput [17] $end
$var wire 1 d keyinput [16] $end
$var wire 1 e keyinput [15] $end
$var wire 1 f keyinput [14] $end
$var wire 1 g keyinput [13] $end
$var wire 1 h keyinput [12] $end
$var wire 1 i keyinput [11] $end
$var wire 1 j keyinput [10] $end
$var wire 1 k keyinput [9] $end
$var wire 1 l keyinput [8] $end
$var wire 1 m keyinput [7] $end
$var wire 1 n keyinput [6] $end
$var wire 1 o keyinput [5] $end
$var wire 1 p keyinput [4] $end
$var wire 1 q keyinput [3] $end
$var wire 1 r keyinput [2] $end
$var wire 1 s keyinput [1] $end
$var wire 1 t keyinput [0] $end
$var wire 1 $ result_o [16] $end
$var wire 1 % result_o [15] $end
$var wire 1 & result_o [14] $end
$var wire 1 ' result_o [13] $end
$var wire 1 ( result_o [12] $end
$var wire 1 ) result_o [11] $end
$var wire 1 * result_o [10] $end
$var wire 1 + result_o [9] $end
$var wire 1 , result_o [8] $end
$var wire 1 - result_o [7] $end
$var wire 1 . result_o [6] $end
$var wire 1 / result_o [5] $end
$var wire 1 0 result_o [4] $end
$var wire 1 1 result_o [3] $end
$var wire 1 2 result_o [2] $end
$var wire 1 3 result_o [1] $end
$var wire 1 4 result_o [0] $end
$var wire 1 u n98 $end
$var wire 1 v n99 $end
$var wire 1 w xenc16 $end
$var wire 1 x xenc23 $end
$var wire 1 y xenc2 $end
$var wire 1 z n107 $end
$var wire 1 { n115 $end
$var wire 1 | xenc10 $end
$var wire 1 } n116 $end
$var wire 1 ~ n119 $end
$var wire 1 !! n120 $end
$var wire 1 "! n131 $end
$var wire 1 #! n132 $end
$var wire 1 $! n134 $end
$var wire 1 %! n135 $end
$var wire 1 &! n138 $end
$var wire 1 '! xenc12 $end
$var wire 1 (! n139 $end
$var wire 1 )! n142 $end
$var wire 1 *! n143 $end
$var wire 1 +! xenc26 $end
$var wire 1 ,! xenc0 $end
$var wire 1 -! n148 $end
$var wire 1 .! n162 $end
$var wire 1 /! n163 $end
$var wire 1 0! n166 $end
$var wire 1 1! n167 $end
$var wire 1 2! n178 $end
$var wire 1 3! n179 $end
$var wire 1 4! xenc30 $end
$var wire 1 5! n190 $end
$var wire 1 6! n195 $end
$var wire 1 7! n196 $end
$var wire 1 8! xenc7 $end
$var wire 1 9! n100 $end
$var wire 1 :! n89 $end
$var wire 1 ;! n165 $end
$var wire 1 <! n85 $end
$var wire 1 =! n158 $end
$var wire 1 >! n159 $end
$var wire 1 ?! n157 $end
$var wire 1 @! n160 $end
$var wire 1 A! n161 $end
$var wire 1 B! n111 $end
$var wire 1 C! n200 $end
$var wire 1 D! n102 $end
$var wire 1 E! n97 $end
$var wire 1 F! xenc19 $end
$var wire 1 G! n127 $end
$var wire 1 H! n169 $end
$var wire 1 I! n201 $end
$var wire 1 J! n183 $end
$var wire 1 K! n108 $end
$var wire 1 L! n194 $end
$var wire 1 M! n198 $end
$var wire 1 N! n104 $end
$var wire 1 O! n173 $end
$var wire 1 P! n170 $end
$var wire 1 Q! xenc6 $end
$var wire 1 R! xenc4 $end
$var wire 1 S! xenc24 $end
$var wire 1 T! n88 $end
$var wire 1 U! xenc25 $end
$var wire 1 V! n185 $end
$var wire 1 W! n103 $end
$var wire 1 X! xenc3 $end
$var wire 1 Y! n92 $end
$var wire 1 Z! n199 $end
$var wire 1 [! n112 $end
$var wire 1 \! n125 $end
$var wire 1 ]! xenc13 $end
$var wire 1 ^! n126 $end
$var wire 1 _! n122 $end
$var wire 1 `! n181 $end
$var wire 1 a! n180 $end
$var wire 1 b! n182 $end
$var wire 1 c! n171 $end
$var wire 1 d! xenc27 $end
$var wire 1 e! n90 $end
$var wire 1 f! xenc9 $end
$var wire 1 g! n192 $end
$var wire 1 h! n193 $end
$var wire 1 i! xenc5 $end
$var wire 1 j! n93 $end
$var wire 1 k! n105 $end
$var wire 1 l! n96 $end
$var wire 1 m! n91 $end
$var wire 1 n! n113 $end
$var wire 1 o! n110 $end
$var wire 1 p! n94 $end
$var wire 1 q! n114 $end
$var wire 1 r! n154 $end
$var wire 1 s! n155 $end
$var wire 1 t! n152 $end
$var wire 1 u! n156 $end
$var wire 1 v! xenc14 $end
$var wire 1 w! xenc18 $end
$var wire 1 x! n175 $end
$var wire 1 y! n177 $end
$var wire 1 z! n176 $end
$var wire 1 {! n188 $end
$var wire 1 |! n186 $end
$var wire 1 }! n187 $end
$var wire 1 ~! n87 $end
$var wire 1 !" n149 $end
$var wire 1 "" n150 $end
$var wire 1 #" xenc20 $end
$var wire 1 $" n151 $end
$var wire 1 %" xenc28 $end
$var wire 1 &" n129 $end
$var wire 1 '" n128 $end
$var wire 1 (" n130 $end
$var wire 1 )" n174 $end
$var wire 1 *" n147 $end
$var wire 1 +" n172 $end
$var wire 1 ," n191 $end
$var wire 1 -" n189 $end
$var wire 1 ." xenc11 $end
$var wire 1 /" xenc22 $end
$var wire 1 0" n164 $end
$var wire 1 1" xenc17 $end
$var wire 1 2" n133 $end
$var wire 1 3" xenc31 $end
$var wire 1 4" n117 $end
$var wire 1 5" n86 $end
$var wire 1 6" xenc8 $end
$var wire 1 7" n121 $end
$var wire 1 8" xenc21 $end
$var wire 1 9" n168 $end
$var wire 1 :" xenc29 $end
$var wire 1 ;" n101 $end
$var wire 1 <" n124 $end
$var wire 1 =" n118 $end
$var wire 1 >" n123 $end
$var wire 1 ?" n136 $end
$var wire 1 @" xenc15 $end
$var wire 1 A" n137 $end
$var wire 1 B" n140 $end
$var wire 1 C" n141 $end
$var wire 1 D" n144 $end
$var wire 1 E" n145 $end
$var wire 1 F" xenc1 $end
$var wire 1 G" n146 $end
$var wire 1 H" n95 $end
$var wire 1 I" n153 $end
$var wire 1 J" n184 $end
$var wire 1 K" n109 $end
$var wire 1 L" n106 $end
$var wire 1 M" n197 $end
$var wire 1 N" n202 $end
$upscope $end
$upscope $end
$enddefinitions $end
#0
$dumpvars
b0 !
b0 "
b11000010010111000001000110110 #
14
03
02
01
00
0/
1.
0-
1,
0+
0*
0)
0(
0'
0&
0%
0$
0u
0v
0w
0x
0y
0z
0{
0|
0}
1~
0!!
0"!
0#!
0$!
0%!
0&!
0'!
0(!
0)!
0*!
0+!
0,!
0-!
0.!
0/!
00!
01!
02!
03!
04!
05!
06!
07!
08!
19!
0:!
1;!
0<!
1=!
1>!
0?!
0@!
0A!
1B!
1C!
0D!
1E!
1F!
0G!
0H!
0I!
1J!
1K!
0L!
0M!
0N!
0O!
0P!
0Q!
1R!
1S!
0T!
0U!
0V!
0W!
1X!
0Y!
1Z!
1[!
0\!
0]!
0^!
0_!
0`!
1a!
1b!
0c!
0d!
0e!
1f!
0g!
1h!
1i!
0j!
1k!
0l!
0m!
1n!
0o!
0p!
1q!
1r!
1s!
0t!
0u!
1v!
1w!
1x!
0y!
1z!
1{!
1|!
1}!
0~!
1!"
1""
0#"
0$"
0%"
0&"
0'"
1("
1)"
0*"
0+"
1,"
0-"
0."
1/"
10"
11"
12"
13"
14"
15"
16"
17"
08"
19"
1:"
1;"
1<"
0="
0>"
1?"
1@"
1A"
1B"
1C"
1D"
1E"
1F"
0G"
1H"
1I"
0J"
1K"
0L"
1M"
1N"
0t
1s
1r
0q
1p
1o
0n
0m
0l
1k
0j
0i
0h
0g
0f
1e
1d
1c
0b
1a
0`
0_
1^
0]
0\
0[
0Z
1Y
1X
0W
0V
0U
0T
0S
0R
0Q
0P
0O
0N
0M
0L
0K
0J
0I
0H
0G
0F
0E
0D
0C
0B
0A
0@
0?
0>
0=
0<
0;
0:
09
08
07
06
05
$end
#10000
b10100110101111 !
b111101000011011 "
1T
1*"
1S
0E"
1)!
1Q
1^!
1P
1\!
1K
1c!
1I
1V!
1H
1+"
1G
1@!
1F
1D
0N"
1C
1G"
1B
1>"
18"
0C"
1&!
0A"
0@"
1$!
02"
01"
1"!
1A
0?"
0("
1&"
1?
0H"
0F!
1W!
1]!
1'"
1%"
0q!
1="
1p!
1_!
07"
1=
0B!
1m!
1<
0C!
1D!
19
0|!
1y!
05"
12!
17
0=!
1.!
1?!
1u!
0s!
1t!
1$"
1#"
1%
1&
1(
1z
1x
1}
1|
1#!
1*!
11
10
1/!
13!
1v
1%!
00
1+
0(
0&
1-
1y
#20000
b1000100000000 !
b1000100010001 "
0S
1E"
0)!
1C"
0&!
1A"
1@"
17"
0Q
1?"
0$!
12"
11"
0"!
1("
0&"
0'"
0%"
1q!
0="
0p!
1L
1H!
0J!
1e!
1d!
0b!
1`!
1L!
0h!
0f!
1g!
1."
09!
1u
1:!
0M"
16!
0K
0c!
1M"
06!
1h!
1f!
0g!
0."
1b!
0`!
0I
1|!
0y!
15"
02!
0G
1=!
0.!
0?!
0u!
1s!
0t!
0$"
0#"
0F
0D
1N"
0C
0G"
0B
0>"
08"
0A
0^!
0_!
0?
1H"
1F!
0W!
0]!
0=
1B!
0m!
0D!
09
0V!
18
0x!
0v!
1A!
0;!
10!
1<!
00"
0/"
1.!
0>!
1?!
1u!
07
0@!
10"
1/"
0.!
1>!
0?!
0u!
03!
1'
0}
0|
0#!
0*!
0/!
0%
0v
0z
0x
10
01
0y
0-
#30000
b1000000100010110 !
b1110011001110 "
0T
0*"
1S
0E"
1)!
1R
1>"
18"
0C"
1&!
1Q
1^!
0A"
0@"
1$!
02"
01"
1"!
0P
0\!
12"
11"
0"!
1N
1N!
04"
03"
1{
1M
0B!
1m!
1D!
0L
0H!
1J!
0e!
0d!
0L!
19!
0u
0:!
1J
1J"
1U!
1I
1V!
1P!
1C
1G"
1B
0B"
1@
1\!
02"
01"
1"!
08
1x!
1v!
0A!
1;!
00!
0<!
15
1$"
1#"
0I"
13!
0'
15!
17!
1z
1x
0+
1}
1|
1!!
1(!
1'!
00
1/
1+!
12
0.
1y
18!
1)
1(
1%
#35000
b100010010000010 !
b11101111001101 "
1T
1*"
0S
1E"
0)!
1C"
1L
1H!
0J!
1e!
1d!
1L!
09!
1u
1:!
1K
1c!
0M"
16!
0h!
0f!
1g!
1."
0,"
1-"
14!
0b!
1`!
0a!
06"
12!
0J
0J"
0U!
1,"
0-"
04!
0P!
1a!
16"
02!
1G
1@!
0B
1B"
0&!
1A"
1@"
0$!
12"
11"
0"!
0@
0\!
1=
0K!
1L"
1w
1I!
0<
0H!
1:
1J"
1U!
0,"
1-"
14!
1P!
0a!
06"
12!
16
1u!
05
0$"
0#"
1I"
1/!
0}
0|
0y
0%!
1*!
11
0/
11!
1v
0(
0)
08!
1-!
13
1'
1-
1&
0%
#37000
b1000100101000011 !
b1111111111111111 "
1S
0E"
1)!
0C"
1&!
0A"
0@"
1$!
1P
1\!
02"
01"
1"!
1O
0E!
1W!
1]!
1_!
07"
1J
0{!
1~!
0}!
1y!
05"
1F
0s!
1t!
1$"
1#"
1E
0""
1$
1D
0N"
1>
0[!
1o!
0K"
1Y!
0Z!
0X!
0=
1K!
0I!
1J!
0e!
0d!
1b!
0`!
1a!
16"
1<
1H!
0J!
1e!
1d!
0b!
1`!
0a!
06"
0:
1{!
0~!
1}!
0y!
15"
19
0|!
1y!
05"
06
0u!
1s!
0t!
0$"
0#"
1""
0$
15
1$"
1#"
0""
1$
05!
0z
0x
1}
1|
0!!
1#!
1%!
0-!
0+!
02
01
03
1.
0-
1y
1)
#47000
b1010101111001101 !
b0 "
0T
1N"
0S
1E"
0)!
1C"
0&!
1A"
1@"
0$!
12"
11"
0"!
17"
0R
0>"
08"
0Q
0^!
0_!
0P
0\!
0O
1E!
0W!
0]!
0N
1[!
0o!
1K"
0L"
0w
0Y!
1Z!
1X!
0M
1B!
0m!
0D!
0L
0H!
1J!
0e!
0d!
1b!
0`!
1a!
16"
0L!
1h!
1f!
0g!
0."
1,"
0-"
04!
19!
0u
0:!
1M"
06!
0K
0c!
0J
0J"
0U!
0P!
0I
1|!
0y!
15"
02!
0H
0+"
0G
0@!
0F
0E
1""
0$
0C
0G"
1B
1>"
18"
1A
1^!
1=
0B!
1m!
1D!
1;
1c!
17
1@!
0I"
0/!
03!
15!
07!
1z
1x
1+
1!!
0#!
0%!
1+!
12
11
0.
0&
1%
#57000
b0 !
b1001000110100 "
1R
0B"
1&!
0A"
0@"
1$!
1P
1\!
02"
01"
1"!
1O
0E!
1W!
1]!
1_!
0<"
1="
1K
0)"
0S!
16!
1g!
1."
1`!
1T!
1H
1+"
0D
0*"
0B
1B"
0&!
1A"
1@"
0$!
12"
11"
0"!
1<"
0="
0A
0^!
0_!
0>
0N!
14"
13"
0{
0=
1B!
0m!
0D!
0<
1C!
0;
1)"
1S!
06!
0g!
0."
0`!
0T!
09
0V!
07
0@!
05
0$"
0#"
1I"
01!
05!
0z
0x
0}
0|
0!!
0(!
0'!
13!
1#!
1%!
1/
01
10
1(
1.
0y
0)
0'
0%
#67000
b1000100010001 !
b1110111010101010 "
1S
0E"
1)!
0C"
1&!
0R
0>"
08"
1C"
0&!
1Q
1^!
1_!
0P
0\!
0_!
1M
0B!
1m!
1J
1J"
1U!
1I
1V!
1P!
0H
0+"
1G
1@!
1F
1E
1D
1*"
1@
1\!
1_!
1<
0C!
1D!
18
1+"
1z
1x
0I"
1/!
11!
15!
17!
1}
1|
1(!
1'!
0*!
1-!
11
13
1-
18!
1)
1'
1&
1%
1y
#77000
b101010101010101 !
b1010101010101010 "
0J
0J"
0U!
0P!
0F
1B
1>"
18"
0C"
1&!
0A"
0@"
1$!
02"
01"
1"!
1>
1N!
04"
03"
1{
1:
1J"
1U!
1P!
16
1u!
1!!
0-
1*!
01
00
0/
0+!
02
0.
#87000
b1000000001010001 !
b1000000010000110 "
1R
0B"
0<"
1="
0Q
0^!
1A"
1@"
0$!
12"
11"
0"!
0_!
1<"
0="
0O
1E!
0W!
0]!
0K
0c!
0I
0V!
0P!
0G
0@!
0B
1B"
0<
1C!
0D!
0:
0J"
0U!
08
0+"
06
0u!
15
1$"
1#"
0""
1$
1I"
0/!
03!
07!
0z
0x
01!
05!
0v
0#!
0(!
0'!
10
11
0+
0)
0'
0y
08!
0(
0&
0%
#92000
b1111101011011100 !
b11011100 "
0S
1E"
0)!
1C"
0&!
1Q
1^!
1P
0k!
1"!
1&"
1l!
1N
0[!
1o!
0K"
1L"
1w
1Y!
0E
1""
0$
0D
0*"
1B
0B"
1&!
0A"
0@"
1$!
02"
01"
1A
0?"
0("
1=
0K!
1;
1c!
19
1V!
18
1+"
17
1@!
16
1u!
1/!
11!
13!
15!
1v
0}
0|
0*!
00
0I"
0!!
1y
0%!
1/
0-!
03
10
1.
1%
1-
1+
1)
1(
1'
1&
#94000
b100000010010110 !
b10000001001000 "
0R
1B"
0&!
1A"
1@"
0P
1k!
0l!
0M
1K!
1G
0=!
1.!
1?!
0r!
1t!
0!"
1$
1C
1G"
0A
1?"
0$!
12"
11"
0"!
1("
0&"
0>
1[!
0o!
1K"
0L"
0w
0Y!
0;
0c!
09
0V!
08
0+"
07
1=!
0.!
0?!
1r!
0t!
1!"
0$
05
0$"
0#"
1I"
03!
05!
0v
1!!
0y
1(!
1'!
00
0/
1-!
0%
1}
1|
1%!
1*!
1+!
12
10
0-
13
0.
0+
0)
0(
#104000
b1000000100100 !
b1000000110010010 "
1S
0E"
1)!
0C"
1&!
0A"
0@"
1$!
02"
01"
1"!
0Q
0^!
1A"
1@"
0$!
12"
11"
0"!
1P
0k!
1"!
1&"
1l!
0N
0N!
14"
13"
0{
1M
0K!
1L"
1w
1L
0C!
1I!
0J!
1e!
1d!
1L!
09!
1u
1:!
1D!
0G
0@!
1E
0C
0G"
0@
1k!
0"!
0&"
0l!
1?
0H"
0F!
1W!
1]!
0=
1K!
0L"
0w
0I!
1J!
0e!
0d!
0L!
19!
0u
0:!
18
1+"
06
0u!
0/!
13!
1#!
0I"
01!
1z
1x
1y
0!!
1-
0(!
0'!
0+!
02
1/
1.
0'
1%
1(
0&
#204000
b0 !
b1 "
1T
1*"
0S
1E"
0)!
1C"
0&!
0P
0\!
0M
1B!
0m!
0D!
0L
1C!
0E
0B
0>"
08"
0?
1H"
1F!
0W!
0]!
08
0+"
03!
0#!
0*!
1I"
0z
0x
0}
0|
0%!
0-!
01
03
00
0-
0y
0%
0/
0(
