lockednetlistsimulation/32xor/error_tolerant_type2_adder/sim/error_tolerant_type2_adder16_xor_enc32.v
// Verilog File 
module error_tolerant_type2_adder16_xor_enc32(add1_i,add2_i,keyinput,result_o);

input [15:0] add1_i, add2_i;
input [31:0] keyinput;


output [16:0] result_o;

wire n67, xenc29, n68, xenc12, n70, xenc6, xenc9, xenc24, n74, 
n73, n77, xenc13, n78, n81, n82, n95, n96, n99, n100, 
xenc27, n103, n104, n116, xenc7, n117, n120, xenc2, n121, n124, 
xenc21, n128, xenc31, xenc0, n141, n142, n145, n146, n149, n152, 
n94, n66, n71, n72, n69, n75, n76, n144, n119, n79, 
n80, n126, xenc10, n125, n127, xenc18, n123, n122, n150, n151, 
n147, n148, n83, xenc26, n86, n85, n84, n153, n154, n156, 
xenc15, n155, n130, n131, n129, n133, n132, xenc16, n162, n160, 
n161, xenc19, n163, n138, xenc23, n137, xenc17, n139, n140, xenc8, 
n88, n90, n87, xenc1, n89, n157, xenc22, n159, n158, xenc11, 
n135, n134, n136, n143, n118, xenc25, xenc4, n92, xenc3, n91, 
xenc28, n93, xenc30, n98, n97, n101, n102, n113, xenc14, n112, 
n115, n114, n109, n110, n108, n111, xenc20, n106, xenc5, n105, 
n107;

xor g0(xenc29, n67, add2_i[9]);
xor g1(result_o[8], n68, add2_i[8]);
xor g2(xenc6, xenc12, n70);
xor g3(n70, add2_i[7], add1_i[7]);
xor g4(xenc24, add2_i[6], xenc9);
xor g5(n73, n74, add1_i[6]);
xor g6(xenc13, add2_i[5], n77);
xor g7(n77, n78, add1_i[5]);
xor g8(result_o[4], n81, add2_i[4]);
xor g9(n81, n82, add1_i[4]);
xor g10(result_o[3], n95, n96);
xor g11(n96, add2_i[3], add1_i[3]);
xor g12(result_o[2], add2_i[2], n99);
xor g13(n99, n100, add1_i[2]);
xor g14(result_o[1], xenc27, add2_i[1]);
xor g15(n104, n103, add1_i[1]);
xor g16(result_o[15], n116, xenc7);
xor g17(n117, add2_i[15], add1_i[15]);
xor g18(xenc2, add2_i[14], n120);
xor g19(n120, n121, add1_i[14]);
xor g20(result_o[13], n124, add2_i[13]);
xor g21(n124, xenc21, add1_i[13]);
xor g22(xenc31, n128, add2_i[12]);
xor g23(n128, xenc0, add1_i[12]);
xor g24(result_o[11], n141, n142);
xor g25(n142, add2_i[11], add1_i[11]);
xor g26(result_o[10], add2_i[10], n145);
xor g27(n145, n146, add1_i[10]);
xor g28(n67, n149, add1_i[9]);
xor g29(n68, n152, add1_i[8]);
not g30(n66, n94);
nand g31(result_o[0], n94, n103);
nand g32(n69, n71, n72);
nand g33(n71, add1_i[6], n74);
nand g34(n74, n75, n76);
nand g35(n75, add1_i[5], n78);
nand g36(n76, n77, add2_i[5]);
nand g37(n144, n145, add2_i[10]);
nand g38(n72, xenc9, add2_i[6]);
nand g39(n119, n120, add2_i[14]);
nand g40(n78, n79, n80);
nand g41(n79, add1_i[4], n82);
nand g42(n80, n81, add2_i[4]);
nand g43(n94, add2_i[0], add1_i[0]);
nand g44(n125, n126, xenc10);
nand g45(n126, add1_i[12], xenc0);
nand g46(n127, n128, add2_i[12]);
nand g47(n121, xenc18, n123);
nand g48(n122, add1_i[13], xenc21);
nand g49(n123, n124, add2_i[13]);
nand g50(n149, n150, n151);
nand g51(n150, add1_i[8], n152);
nand g52(n151, add2_i[8], n68);
nand g53(n146, n147, n148);
nand g54(n147, add1_i[9], n149);
nand g55(n148, add2_i[9], n67);
nand g56(n82, n83, xenc26);
nand g57(n83, add1_i[3], n86);
nand g58(n84, add2_i[3], n85);
or g59(n85, n86, add1_i[3]);
nand g60(n152, n153, n154);
nand g61(n153, add1_i[7], n156);
nand g62(n154, add2_i[7], xenc15);
or g63(n155, n156, add1_i[7]);
nand g64(n129, n130, n131);
nand g65(n130, add1_i[11], n133);
nand g66(n131, add2_i[11], n132);
or g67(n132, n133, add1_i[11]);
nand g68(n160, xenc16, n162);
nand g69(n161, add2_i[5], add1_i[5]);
nand g70(n162, add1_i[4], xenc19, add2_i[4]);
or g71(n163, add2_i[5], add1_i[5]);
nand g72(n137, n138, xenc23);
nand g73(n138, add2_i[9], add1_i[9]);
nand g74(n139, add1_i[8], xenc17, add2_i[8]);
or g75(n140, add2_i[9], add1_i[9]);
nand g76(n86, xenc8, n88);
nand g77(n87, add1_i[2], n90);
nand g78(n88, add2_i[2], xenc1);
or g79(n89, n90, add1_i[2]);
nand g80(n156, n157, xenc22);
nand g81(n157, add1_i[6], n160);
nand g82(n158, add2_i[6], n159);
or g83(n159, n160, add1_i[6]);
nand g84(n133, xenc11, n135);
nand g85(n134, add1_i[10], n137);
nand g86(n135, add2_i[10], n136);
or g87(n136, n137, add1_i[10]);
nand g88(n141, n143, n144);
nand g89(n143, add1_i[10], n146);
nand g90(n116, n118, xenc25);
nand g91(n118, add1_i[14], n121);
nand g92(n90, xenc4, n92);
nand g93(n91, add1_i[1], xenc3);
nand g94(n92, add2_i[1], xenc28);
or g95(n93, add1_i[1], xenc3);
or g96(n103, add2_i[0], add1_i[0]);
nand g97(n95, xenc30, n98);
nand g98(n97, add1_i[2], n100);
nand g99(n98, n99, add2_i[2]);
nand g100(n100, n101, n102);
nand g101(n102, add1_i[1], n103);
nand g102(n101, xenc27, add2_i[1]);
nand g103(n112, n113, xenc14);
nand g104(n113, add2_i[13], add1_i[13]);
nand g105(n114, add1_i[12], n115, add2_i[12]);
or g106(n115, add2_i[13], add1_i[13]);
nand g107(n108, n109, n110);
nand g108(n109, add1_i[14], n112);
nand g109(n110, add2_i[14], n111);
or g110(n111, n112, add1_i[14]);
nand g111(xenc5, xenc20, n106);
nand g112(n105, add1_i[15], n108);
nand g113(n106, add2_i[15], n107);
or g114(n107, n108, add1_i[15]);
xnor g115(xenc0, n129, keyinput[0]);
xor g116(xenc1, n89, keyinput[1]);
xor g117(result_o[14], xenc2, keyinput[2]);
xor g118(xenc3, n66, keyinput[3]);
xnor g119(xenc4, n91, keyinput[4]);
xnor g120(result_o[16], xenc5, keyinput[5]);
xor g121(result_o[7], xenc6, keyinput[6]);
xnor g122(xenc7, n117, keyinput[7]);
xor g123(xenc8, n87, keyinput[8]);
xnor g124(xenc9, n73, keyinput[9]);
xnor g125(xenc10, n127, keyinput[10]);
xnor g126(xenc11, n134, keyinput[11]);
xnor g127(xenc12, n69, keyinput[12]);
xor g128(result_o[5], xenc13, keyinput[13]);
xor g129(xenc14, n114, keyinput[14]);
xnor g130(xenc15, n155, keyinput[15]);
xor g131(xenc16, n161, keyinput[16]);
xor g132(xenc17, n140, keyinput[17]);
xor g133(xenc18, n122, keyinput[18]);
xnor g134(xenc19, n163, keyinput[19]);
xnor g135(xenc20, n105, keyinput[20]);
xnor g136(xenc21, n125, keyinput[21]);
xor g137(xenc22, n158, keyinput[22]);
xnor g138(xenc23, n139, keyinput[23]);
xor g139(result_o[6], xenc24, keyinput[24]);
xor g140(xenc25, n119, keyinput[25]);
xor g141(xenc26, n84, keyinput[26]);
xor g142(xenc27, n104, keyinput[27]);
xor g143(xenc28, n93, keyinput[28]);
xor g144(result_o[9], xenc29, keyinput[29]);
xor g145(xenc30, n97, keyinput[30]);
xor g146(result_o[12], xenc31, keyinput[31]);
endmodule

lockednetlistsimulation/32xor/error_tolerant_type2_adder/sim/error_tolerant_type2_adder16_tb.v
`timescale 1ns / 1ps
//////////////////////////////////////////////////////////////////////////////////
// Company: 
// Engineer: 
// 
// Create Date: 05/05/2020 01:15:36 AM
// Design Name: 
// Module Name: Test_Bench
// Project Name: 
// Target Devices: 
// Tool Versions: 
// Description: 
// 
// Dependencies: 
// 
// Revision:
// Revision 0.01 - File Created
// Additional Comments:
// 
//////////////////////////////////////////////////////////////////////////////////


module error_tolerant_type2_adder16_tb;
reg [15:0]add1_i;
reg [15:0]add2_i;
reg [31:0]keyinput = 32'h00B89E0F;
wire [16:0]result_o;


error_tolerant_type2_adder16_xor_enc32 eta(add1_i,add2_i,keyinput,result_o);

initial begin
   $dumpfile("error_tolerant_type2_adder16_simgate.vcd");
   $dumpvars(3,error_tolerant_type2_adder16_tb);

   
   add1_i = 16'h0000;
   add2_i = 16'h0000;
   #10
   add1_i = 16'h29AF;
   add2_i = 16'h7A1B;
   #10
   add1_i = 16'h1100;
   add2_i = 16'h1111;
   #10
   add1_i = 16'h8116;
   add2_i = 16'h1CCE;
   #5
   add1_i = 16'h4482;
   add2_i = 16'h3BCD;
   #5
   add1_i = 16'h8943;
   add2_i = 16'hFFFF;
   #10
   add1_i = 16'hABCD;
   add2_i = 16'h0000;
   #10
   add1_i = 16'h0000;
   add2_i = 16'h1234;
   #10
   add1_i = 16'h1111;
   add2_i = 16'hEEAA;
  #10
   add1_i = 16'h5555;
   add2_i = 16'hAAAA;
  #10
   add1_i = 16'h8051;
   add2_i = 16'h8086;
  #5
  add1_i = 16'hFADC;
  add2_i = 16'h00DC;
 #5
  add1_i = 16'h4096;
  add2_i = 16'h2048;
 #10
  add1_i = 16'h1024;
  add2_i = 16'h8192;
  #100
   add1_i = 16'h0000;
   add2_i = 16'h0001;
  #100
  
   $finish;
    
   
 end

initial begin

$monitor($time , " add1_i= %h, add2_i = %h, keyinput= %h, result_o = %h ",add1_i, add2_i, keyinput, result_o);
end
	
	
	
endmodule

lockednetlistsimulation/32xor/error_tolerant_type2_adder/sim/error_tolerant_type2_adder16_simgate.vcd
$date
	Sun Sep 20 15:28:18 2020
$end
$version
	ModelSim Version 6.6d
$end
$timescale
	1ps
$end
$scope module error_tolerant_type2_adder16_tb $end
$var reg 16 ! add1_i [15:0] $end
$var reg 16 " add2_i [15:0] $end
$var reg 32 # keyinput [31:0] $end
$var wire 1 $ result_o [16] $end
$var wire 1 % result_o [15] $end
$var wire 1 & result_o [14] $end
$var wire 1 ' result_o [13] $end
$var wire 1 ( result_o [12] $end
$var wire 1 ) result_o [11] $end
$var wire 1 * result_o [10] $end
$var wire 1 + result_o [9] $end
$var wire 1 , result_o [8] $end
$var wire 1 - result_o [7] $end
$var wire 1 . result_o [6] $end
$var wire 1 / result_o [5] $end
$var wire 1 0 result_o [4] $end
$var wire 1 1 result_o [3] $end
$var wire 1 2 result_o [2] $end
$var wire 1 3 result_o [1] $end
$var wire 1 4 result_o [0] $end
$scope module eta $end
$var wire 1 5 add1_i [15] $end
$var wire 1 6 add1_i [14] $end
$var wire 1 7 add1_i [13] $end
$var wire 1 8 add1_i [12] $end
$var wire 1 9 add1_i [11] $end
$var wire 1 : add1_i [10] $end
$var wire 1 ; add1_i [9] $end
$var wire 1 < add1_i [8] $end
$var wire 1 = add1_i [7] $end
$var wire 1 > add1_i [6] $end
$var wire 1 ? add1_i [5] $end
$var wire 1 @ add1_i [4] $end
$var wire 1 A add1_i [3] $end
$var wire 1 B add1_i [2] $end
$var wire 1 C add1_i [1] $end
$var wire 1 D add1_i [0] $end
$var wire 1 E add2_i [15] $end
$var wire 1 F add2_i [14] $end
$var wire 1 G add2_i [13] $end
$var wire 1 H add2_i [12] $end
$var wire 1 I add2_i [11] $end
$var wire 1 J add2_i [10] $end
$var wire 1 K add2_i [9] $end
$var wire 1 L add2_i [8] $end
$var wire 1 M add2_i [7] $end
$var wire 1 N add2_i [6] $end
$var wire 1 O add2_i [5] $end
$var wire 1 P add2_i [4] $end
$var wire 1 Q add2_i [3] $end
$var wire 1 R add2_i [2] $end
$var wire 1 S add2_i [1] $end
$var wire 1 T add2_i [0] $end
$var wire 1 U keyinput [31] $end
$var wire 1 V keyinput [30] $end
$var wire 1 W keyinput [29] $end
$var wire 1 X keyinput [28] $end
$var wire 1 Y keyinput [27] $end
$var wire 1 Z keyinput [26] $end
$var wire 1 [ keyinput [25] $end
$var wire 1 \ keyinput [24] $end
$var wire 1 ] keyinput [23] $end
$var wire 1 ^ keyinput [22] $end
$var wire 1 _ keyinput [21] $end
$var wire 1 ` keyinput [20] $end
$var wire 1 a keyinput [19] $end
$var wire 1 b keyinput [18] $end
$var wire 1 c keyinput [17] $end
$var wire 1 d keyinput [16] $end
$var wire 1 e keyinput [15] $end
$var wire 1 f keyinput [14] $end
$var wire 1 g keyinput [13] $end
$var wire 1 h keyinput [12] $end
$var wire 1 i keyinput [11] $end
$var wire 1 j keyinput [10] $end
$var wire 1 k keyinput [9] $end
$var wire 1 l keyinput [8] $end
$var wire 1 m keyinput [7] $end
$var wire 1 n keyinput [6] $end
$var wire 1 o keyinput [5] $end
$var wire 1 p keyinput [4] $end
$var wire 1 q keyinput [3] $end
$var wire 1 r keyinput [2] $end
$var wire 1 s keyinput [1] $end
$var wire 1 t keyinput [0] $end
$var wire 1 $ result_o [16] $end
$var wire 1 % result_o [15] $end
$var wire 1 & result_o [14] $end
$var wire 1 ' result_o [13] $end
$var wire 1 ( result_o [12] $end
$var wire 1 ) result_o [11] $end
$var wire 1 * result_o [10] $end
$var wire 1 + result_o [9] $end
$var wire 1 , result_o [8] $end
$var wire 1 - result_o [7] $end
$var wire 1 . result_o [6] $end
$var wire 1 / result_o [5] $end
$var wire 1 0 result_o [4] $end
$var wire 1 1 result_o [3] $end
$var wire 1 2 result_o [2] $end
$var wire 1 3 result_o [1] $end
$var wire 1 4 result_o [0] $end
$var wire 1 u n67 $end
$var wire 1 v xenc29 $end
$var wire 1 w n68 $end
$var wire 1 x xenc12 $end
$var wire 1 y n70 $end
$var wire 1 z xenc6 $end
$var wire 1 { xenc9 $end
$var wire 1 | xenc24 $end
$var wire 1 } n74 $end
$var wire 1 ~ n73 $end
$var wire 1 !! n77 $end
$var wire 1 "! xenc13 $end
$var wire 1 #! n78 $end
$var wire 1 $! n81 $end
$var wire 1 %! n82 $end
$var wire 1 &! n95 $end
$var wire 1 '! n96 $end
$var wire 1 (! n99 $end
$var wire 1 )! n100 $end
$var wire 1 *! xenc27 $end
$var wire 1 +! n103 $end
$var wire 1 ,! n104 $end
$var wire 1 -! n116 $end
$var wire 1 .! xenc7 $end
$var wire 1 /! n117 $end
$var wire 1 0! n120 $end
$var wire 1 1! xenc2 $end
$var wire 1 2! n121 $end
$var wire 1 3! n124 $end
$var wire 1 4! xenc21 $end
$var wire 1 5! n128 $end
$var wire 1 6! xenc31 $end
$var wire 1 7! xenc0 $end
$var wire 1 8! n141 $end
$var wire 1 9! n142 $end
$var wire 1 :! n145 $end
$var wire 1 ;! n146 $end
$var wire 1 <! n149 $end
$var wire 1 =! n152 $end
$var wire 1 >! n94 $end
$var wire 1 ?! n66 $end
$var wire 1 @! n71 $end
$var wire 1 A! n72 $end
$var wire 1 B! n69 $end
$var wire 1 C! n75 $end
$var wire 1 D! n76 $end
$var wire 1 E! n144 $end
$var wire 1 F! n119 $end
$var wire 1 G! n79 $end
$var wire 1 H! n80 $end
$var wire 1 I! n126 $end
$var wire 1 J! xenc10 $end
$var wire 1 K! n125 $end
$var wire 1 L! n127 $end
$var wire 1 M! xenc18 $end
$var wire 1 N! n123 $end
$var wire 1 O! n122 $end
$var wire 1 P! n150 $end
$var wire 1 Q! n151 $end
$var wire 1 R! n147 $end
$var wire 1 S! n148 $end
$var wire 1 T! n83 $end
$var wire 1 U! xenc26 $end
$var wire 1 V! n86 $end
$var wire 1 W! n85 $end
$var wire 1 X! n84 $end
$var wire 1 Y! n153 $end
$var wire 1 Z! n154 $end
$var wire 1 [! n156 $end
$var wire 1 \! xenc15 $end
$var wire 1 ]! n155 $end
$var wire 1 ^! n130 $end
$var wire 1 _! n131 $end
$var wire 1 `! n129 $end
$var wire 1 a! n133 $end
$var wire 1 b! n132 $end
$var wire 1 c! xenc16 $end
$var wire 1 d! n162 $end
$var wire 1 e! n160 $end
$var wire 1 f! n161 $end
$var wire 1 g! xenc19 $end
$var wire 1 h! n163 $end
$var wire 1 i! n138 $end
$var wire 1 j! xenc23 $end
$var wire 1 k! n137 $end
$var wire 1 l! xenc17 $end
$var wire 1 m! n139 $end
$var wire 1 n! n140 $end
$var wire 1 o! xenc8 $end
$var wire 1 p! n88 $end
$var wire 1 q! n90 $end
$var wire 1 r! n87 $end
$var wire 1 s! xenc1 $end
$var wire 1 t! n89 $end
$var wire 1 u! n157 $end
$var wire 1 v! xenc22 $end
$var wire 1 w! n159 $end
$var wire 1 x! n158 $end
$var wire 1 y! xenc11 $end
$var wire 1 z! n135 $end
$var wire 1 {! n134 $end
$var wire 1 |! n136 $end
$var wire 1 }! n143 $end
$var wire 1 ~! n118 $end
$var wire 1 !" xenc25 $end
$var wire 1 "" xenc4 $end
$var wire 1 #" n92 $end
$var wire 1 $" xenc3 $end
$var wire 1 %" n91 $end
$var wire 1 &" xenc28 $end
$var wire 1 '" n93 $end
$var wire 1 (" xenc30 $end
$var wire 1 )" n98 $end
$var wire 1 *" n97 $end
$var wire 1 +" n101 $end
$var wire 1 ," n102 $end
$var wire 1 -" n113 $end
$var wire 1 ." xenc14 $end
$var wire 1 /" n112 $end
$var wire 1 0" n115 $end
$var wire 1 1" n114 $end
$var wire 1 2" n109 $end
$var wire 1 3" n110 $end
$var wire 1 4" n108 $end
$var wire 1 5" n111 $end
$var wire 1 6" xenc20 $end
$var wire 1 7" n106 $end
$var wire 1 8" xenc5 $end
$var wire 1 9" n105 $end
$var wire 1 :" n107 $end
$upscope $end
$upscope $end
$enddefinitions $end
#0
$dumpvars
b0 !
b0 "
b101110001001111000001111 #
14
03
02
01
00
0/
0.
0-
0,
0+
0*
0)
0(
0'
1&
1%
1$
0u
0v
0w
0x
0y
0z
0{
0|
0}
0~
0!!
0"!
0#!
0$!
0%!
0&!
0'!
0(!
0)!
0*!
0+!
0,!
0-!
1.!
0/!
00!
01!
02!
03!
04!
05!
06!
07!
08!
09!
0:!
0;!
0<!
0=!
1>!
0?!
1@!
1A!
0B!
1C!
1D!
1E!
1F!
1G!
1H!
1I!
1J!
0K!
1L!
1M!
1N!
1O!
1P!
1Q!
1R!
1S!
1T!
1U!
0V!
0W!
1X!
1Y!
1Z!
0[!
0\!
0]!
1^!
1_!
0`!
0a!
0b!
1c!
1d!
0e!
1f!
0g!
0h!
1i!
1j!
0k!
0l!
1m!
0n!
1o!
1p!
1q!
1r!
0s!
1t!
1u!
1v!
0w!
1x!
1y!
1z!
1{!
0|!
1}!
1~!
1!"
0""
1#"
1$"
1%"
1&"
1'"
1("
1)"
1*"
1+"
1,"
1-"
1."
0/"
00"
11"
12"
13"
04"
05"
16"
17"
08"
19"
0:"
1t
1s
1r
1q
0p
0o
0n
0m
0l
1k
1j
1i
1h
0g
0f
1e
0d
0c
0b
1a
1`
1_
0^
1]
0\
0[
0Z
0Y
0X
0W
0V
0U
0T
0S
0R
0Q
0P
0O
0N
0M
0L
0K
0J
0I
0H
0G
0F
0E
0D
0C
0B
0A
0@
0?
0>
0=
0<
0;
0:
09
08
07
06
05
$end
#10000
b10100110101111 !
b111101000011011 "
1T
1+!
04
1S
0#"
1Q
1P
1K
1n!
1I
1H
1G
10"
1F
1D
0>!
14
1?!
1C
0,"
1)!
0%"
1B
0*"
0r!
1A
1W!
0X!
1?
1h!
1=
1]!
1<
19
1b!
0_!
1`!
17
0-"
1/"
15"
03"
14"
1:"
13!
0N!
12!
17!
1w
1y
1\!
1!!
1g!
0U!
1%!
0o!
1V!
0T!
0("
1&!
1""
0$"
1%"
11!
16!
1v
1l!
10
13
1+
1(
0&
0""
11
1$!
0H!
1#!
0C!
1}
1"!
1z
1,
15!
0L!
10!
0F!
01!
0!"
1-!
06!
0J!
1K!
1-
1/
00
0!!
1~
1{
0"!
14!
0O!
0(
0%
1&
03!
1N!
02!
0M!
12!
0/
1|
1.
1'
#20000
b1000100000000 !
b1000100010001 "
0S
1#"
0Q
1X!
1L
0m!
0Q!
1<!
0K
0n!
0I
1_!
0`!
0G
1-"
0/"
05"
13"
04"
0:"
0F
1F!
0D
1>!
04
0?!
0C
1,"
0)!
1*"
0'"
0B
1r!
0A
1T!
0?
0h!
1C!
0}
0=
0]!
09
0b!
18
01"
0I!
07
00"
11"
1O!
13!
1M!
02!
05!
1L!
0y
0\!
1!!
0~
0g!
1o!
0V!
0W!
1,!
0&"
1("
0&!
1$"
1'"
11!
1!"
0-!
07!
1I!
0v
0l!
1m!
0,
1u
1U!
0%!
03
0$!
1H!
0#!
1v
15!
0L!
1%
0&
1&"
01
1*!
0{
1"!
0z
00!
01!
0-
1/
0|
13
10
0!!
0"!
0.
1&
0/
#30000
b1000000100010110 !
b1110011001110 "
0T
0+!
14
1S
0+"
1)!
0#"
1R
1Q
0P
1N
1M
0L
1Q!
0<!
1J
1I
1C
0%"
1B
0*"
0r!
1@
08
15
1:"
1/!
05!
1L!
1$!
0o!
1V!
1W!
0X!
0("
1&!
1""
19!
1*
1,
0u
1y
1|
1'!
12
03
1.
1z
0v
1)
0U!
1%!
0G!
1#!
16!
1J!
0K!
0.!
0%
04!
1(
0$!
1!!
0+
1-
1"!
00
03!
0'
1/
#35000
b100010010000010 !
b11101111001101 "
1T
1+!
0,"
04
0S
1+"
1#"
0q!
1r!
1L
0Q!
1<!
1K
1n!
0J
1G
10"
0B
1*"
0t!
0@
1G!
0#!
1=
1]!
0<
1:
1|!
16
15"
05
0:"
0/!
10!
1:!
0w
1Q!
0<!
0y
1\!
0Z!
1=!
1$!
0!!
1(!
0)"
1s!
0p!
1("
1'
1v
1l!
13
1o!
0,!
0*!
1+
02
0"!
10
1w
0Q!
1<!
0z
11!
1.!
1%
0&
0-
0,
1u
0S!
1;!
0}!
18!
0/
03
0v
0:!
0)
0*
0+
#40000
b1000100101000011 !
b1111111111111111 "
1S
0#"
1q!
1t!
1P
0H!
1#!
1O
1h!
1J
0z!
1a!
1b!
0_!
1`!
1F
03"
14"
1:"
0F!
1E
07"
18"
1D
0>!
14
1?!
1>
1w!
0x!
0=
0]!
1<
0m!
0P!
0:
1}!
08!
0|!
1z!
0a!
0b!
1_!
0`!
19
1b!
0_!
1`!
06
05"
13"
04"
0:"
17"
08"
15
1:"
07"
18"
00!
1F!
09!
1:!
0E!
18!
1)
0w
1Q!
0j!
1k!
1|!
0z!
1a!
0^!
1y
0\!
1Z!
0=!
1P!
0<!
1~
0v!
1[!
1]!
0$"
1%"
0$
17!
1"!
1g!
00
1!!
0D!
1}
0@!
1B!
13
0s!
1p!
0V!
0W!
1X!
1U!
0%!
0"!
0~
1x
15!
0L!
0""
1\!
0Z!
1=!
0P!
1<!
1,
06!
0J!
1K!
0$!
1H!
0#!
10
0!!
1D!
0}
1@!
0B!
14!
0(
13!
0N!
12!
1"!
1~
0x
1z
1{
0A!
1B!
1/
0'
10!
0F!
01!
0!"
1-!
0|
1x
1-
0z
0.
0%
1&
0-
#50000
b1010101111001101 !
b0 "
0T
1>!
04
0?!
0S
1#"
0R
1)"
0&!
0Q
0P
0O
0h!
0N
1x!
1A!
0B!
0M
1Z!
0=!
1P!
0<!
0L
1m!
0K
0n!
1S!
0;!
0J
1z!
0a!
1^!
1E!
08!
0I
1_!
0`!
0H
1L!
0G
00"
1N!
02!
0F
1F!
0E
17"
08"
0C
1,"
0)!
0'"
1B
0r!
1A
1W!
1=
0Y!
1=!
0P!
1<!
1;
1n!
0R!
1;!
17
10"
0O!
03!
0M!
12!
0o!
1V!
0T!
1%!
1,!
0&"
1/!
1$
11!
1!"
0-!
16!
1J!
0K!
19!
07!
1*
1v
0,
1j!
0k!
0|!
0u
1|
0x
1v!
0[!
1Y!
0=!
1P!
0<!
1R!
0;!
0"!
0g!
00
12
11
03
1$"
1'"
1&"
0/
1w
1u
0:!
1z
1.
1+
05!
04!
1O!
1(
1%
0&
0.!
1*!
1$!
10
13
0%
13!
1M!
02!
06!
1-
0*
1,
0(
00!
1'
01!
1&
#60000
b0 !
b1001000110100 "
1R
0)"
1&!
1P
0H!
1#!
1O
1h!
1K
0i!
1k!
1|!
0S!
1;!
1H
0D
0+!
14
0B
1r!
0A
1T!
0%!
0>
0w!
0=
0]!
0<
0;
1i!
0k!
0|!
09
0b!
07
00"
05
0:"
0/!
03!
09!
0u
1S!
0;!
0w
0y
0\!
0~
0'!
0$!
1H!
0#!
0(!
1)"
0&!
1o!
0V!
0W!
0,!
16!
1"!
1g!
01
1/
1(
0*!
0{
0z
0,
0)
0'
1.!
1%
0-
0|
03
0.
#70000
b1000100010001 !
b1110111010101010 "
1S
0#"
0R
1Q
0P
1M
1J
1I
0H
1G
10"
1F
1E
1D
1+!
04
1@
1<
18
15!
1w
1$!
1,!
1/!
11!
1'
19!
1*
1y
1'!
02
13
11
1z
1)
0&
0.!
1*!
0+"
1)!
1,
03
1(!
0%
1-
12
#80000
b101010101010101 !
b1010101010101010 "
0J
0F
1B
0*"
0r!
1>
1w!
1:
1|!
16
15"
10!
1:!
1~
0(!
0o!
1V!
1W!
0X!
0("
1&!
01
0U!
1%!
0G!
1#!
02
1{
1|
0$!
1!!
0D!
1}
0@!
1B!
0"!
0~
1x
00
1.
0z
0{
0/
0|
0-
0.
#90000
b1000000001010001 !
b1000000010000110 "
1R
0Q
1X!
0O
0h!
1D!
0}
1@!
0B!
0K
0n!
0I
0G
00"
0B
1*"
1r!
0<
0:
0|!
08
06
05"
15
1:"
07"
18"
0/!
0$
00!
05!
0:!
0w
1(!
0)"
1o!
0V!
0W!
1("
0'
09!
0v
0l!
1"!
1~
0x
0g!
0'!
1U!
0%!
1G!
0#!
1$!
0!!
11
1z
1{
1/
0+
0)
0,
0*
06!
01!
1.!
1%
1&
0(
1|
1-
0"!
10
0/
1.
#95000
b1111101011011100 !
b11011100 "
0S
1+"
0)!
1#"
1Q
1P
0H!
1#!
1N
0x!
0A!
1B!
0E
17"
08"
0D
0+!
14
1B
0r!
1A
1W!
0X!
1=
1]!
1;
1n!
19
1b!
18
17
10"
16
15"
10!
13!
15!
19!
1u
1l!
0y
1\!
0Z!
1=!
0U!
1%!
0G!
0o!
1V!
0T!
0,!
1/!
1$
0|
1x
0v!
1[!
0Y!
00
1!!
13
1"!
0.
0.!
0*!
0$!
1H!
1w
1v
1)
16!
1'
11!
0&
1(
1+
1,
10
03
0%
1/
#100000
b100000010010110 !
b10000001001000 "
0R
1)"
0&!
0P
0M
1Z!
1G
0-"
1/"
02"
14"
09"
0N!
12!
0~!
1-!
1C
0%"
0A
1T!
0>
0w!
1x!
0;
0n!
09
0b!
08
07
1-"
0/"
12"
04"
19"
05
0:"
0/!
03!
1N!
02!
1~!
0-!
05!
09!
0u
0l!
0~
1v!
0[!
1Y!
0=!
1'!
1,!
1""
0q!
1r!
1y
00
12
0z
1o!
0V!
0W!
1X!
1*!
0w
0{
1A!
0B!
0v
0)
06!
1.!
1%
0(
0+
1|
0x
0,
13
1U!
0%!
1G!
0#!
0-
1$!
0!!
1z
1.
1-
0"!
10
0/
#110000
b1000000100100 !
b1000000110010010 "
1S
0+"
1)!
0*"
0#"
1q!
0r!
0Q
1P
0H!
1#!
0N
1M
0Z!
1=!
1L
0G
00"
1E
0C
1%"
0@
1?
1h!
0C!
1}
0=
0]!
18
06
05"
00!
15!
0\!
1Z!
0=!
1~
1g!
0$!
1H!
0#!
1C!
0}
0,!
0""
1/!
0'
1,
0|
1!!
0'!
03
0o!
1V!
1W!
0(!
0("
1&!
02
1"!
0.
0.!
0*!
1+"
0)!
1*"
0~
16!
01!
1&
1(
13
1(!
1("
0&!
0%
1/
01
12
#210000
b0 !
b1 "
1T
1+!
04
0S
1#"
0P
0M
0L
0E
0B
1r!
0?
0h!
08
05!
0!!
0g!
0(!
1o!
0V!
0W!
0/!
0,
0y
00
03
1,!
1*!
0z
1.!
02
0"!
06!
0(
0/
1%
0-
13
